tzhworkauto/__init__.py
tzhworkauto/fillsheet.py
tzhworkauto-0.0.3.dist-info/LICENSE
tzhworkauto-0.0.3.dist-info/METADATA
tzhworkauto-0.0.3.dist-info/WHEEL
tzhworkauto-0.0.3.dist-info/top_level.txt
tzhworkauto-0.0.3.dist-info/RECORD
